hdfstream/__init__.py
hdfstream/config.py
hdfstream/connection.py
hdfstream/decoding.py
hdfstream/defaults.py
hdfstream/exceptions.py
hdfstream/remote_dataset.py
hdfstream/remote_directory.py
hdfstream/remote_file.py
hdfstream/remote_group.py
hdfstream/remote_links.py
hdfstream/slice_utils.py
hdfstream/streaming_decoder.py
hdfstream/testing.py
hdfstream/util.py
hdfstream-0.0.23.dist-info/licenses/LICENSE.md
hdfstream-0.0.23.dist-info/METADATA
hdfstream-0.0.23.dist-info/WHEEL
hdfstream-0.0.23.dist-info/top_level.txt
hdfstream-0.0.23.dist-info/RECORD
