Metadata-Version: 2.4
Name: hdfstream
Version: 0.0.23
Summary: Python client for the hdfstream service.
Author-email: John Helly <j.c.helly@durham.ac.uk>
Project-URL: Homepage, https://github.com/jchelly/hdfstream-python
Project-URL: Documentation, https://hdfstream-python.readthedocs.io/en/latest/
Project-URL: Repository, https://github.com/jchelly/hdfstream-python.git
Project-URL: Issues, https://github.com/jchelly/hdfstream-python/issues
Classifier: Programming Language :: Python :: 3
Classifier: License :: OSI Approved :: GNU General Public License v3 (GPLv3)
Classifier: Operating System :: OS Independent
Requires-Python: >=3.10
License-File: LICENSE.md
Requires-Dist: numpy
Requires-Dist: requests
Requires-Dist: msgpack
Requires-Dist: msgpack-numpy
Requires-Dist: tqdm
Requires-Dist: pytest
Requires-Dist: pytest-recording
Requires-Dist: h5py
Requires-Dist: platformdirs
Requires-Dist: pyyaml
Requires-Dist: keyring
Dynamic: license-file
